[{"model": "main.products", "pk": 1, "fields": {"name": "ТАРЕЛКА ЕВРОПЕЙСКИХ СЫРОВ", "description": "Грана Падано, Дор блю, Бри,\r\nвиноград, клубника,\r\nгрецкий орех, липовый мёд", "price": "1200.00", "image": "Product_IMG/l.2213e1973b6b933e8bce55db59c7ac22.jpg", "category": 1}}, {"model": "main.products", "pk": 2, "fields": {"name": "ТАР-ТАР ИЗ ГОВЯЖ", "description": "", "price": "2000.00", "image": "Product_IMG/Beef_TarTar_01.jpg", "category": 1}}, {"model": "main.products", "pk": 3, "fields": {"name": "САЛАТ “ЦЕЗАРЬ” С КРЕВЕТКАМИ", "description": "и листьями романо в соусе цезарь, пшеничными\r\nсухариками и сыром Грана Падано", "price": "630.00", "image": "Product_IMG/ryan-concepcion-w_z0RJCSBiE-unsplash-min-1-1.jpg", "category": 2}}, {"model": "main.products", "pk": 4, "fields": {"name": "ТЁПЛЫЙ САЛАТ С ГОВЯДИНОЙ,", "description": "болгарским перчиком и\r\nхрустящими огурчиками, листьями\r\nайсберга под соусом цезарь", "price": "520.00", "image": "Product_IMG/u-f3cdfbd9c0f24db4359c66b65c20b5f7.jpg", "category": 2}}, {"model": "main.products", "pk": 5, "fields": {"name": "ТОМ ЯМ", "description": "с креветками, кальмарами\r\nи мидиями, сладкими\r\nтоматами, вешенками,\r\nчили и листьями кинзы по\r\nклассическому тайскому\r\nрецепту.\r\nПодаётся с рисом", "price": "1500.00", "image": "Product_IMG/86.jpg", "category": 4}}, {"model": "main.products", "pk": 6, "fields": {"name": "ТАЛЬЯТЕЛЛЕ В СОУСЕ КАРБОНАРА", "description": "на основе желтка, беконом, сыром Грана Падано", "price": "2000.00", "image": "Product_IMG/pasta-karbonara-pasta-alla-carbonara_50865_photo_56238.jpg", "category": 5}}, {"model": "main.products", "pk": 7, "fields": {"name": "КАРТОФЕЛЬ МИНИ", "description": "с жареными шампиньонами и вешенками,\r\nрубленой зеленью", "price": "500.00", "image": "Product_IMG/Depositphotos_78843390_xl-2015_1532470300.jpg", "category": 3}}, {"model": "main.products", "pk": 8, "fields": {"name": "КРЕВЕТКИ В ХРУСТЯЩЕЙ КОРОЧКЕ", "description": "Подаются с соусом чили манго", "price": "1500.00", "image": "Product_IMG/scale_1200.jpeg", "category": 3}}, {"model": "main.products", "pk": 9, "fields": {"name": "БЕФСТРОГАНОВ ИЗ ГОВЯДИНЫ", "description": "с шампиньонами на картофельном пюре\r\nс солёными огурчиками и миксом салатных листьев", "price": "8000.00", "image": "Product_IMG/Stroka-68.-Befstroganov.-Depozit_1581683065-e1581940125674-scaled.jpg", "category": 6}}, {"model": "main.products", "pk": 10, "fields": {"name": "ФЛАНК ГОВЯЖИЙ", "description": "с хрустящими баклажанами,\r\nлёгким салатом\r\nи сливочно-перечным соусом", "price": "9000.00", "image": "Product_IMG/1554277516_prostoj-flank-stejk-v-duhovke-s-maslom-s-zelenyu.jpg", "category": 6}}, {"model": "main.products", "pk": 11, "fields": {"name": "УДОН С КРЕВЕТКАМИ", "description": "болгарским перцем, морковью,\r\nрепчатым луком, цукини и\r\nимбирём с соусом Терияки,\r\nкунжутом, луком пореем", "price": "800.00", "image": "Product_IMG/103_1726235060.jpg", "category": 7}}]